poetrylucidtest/__init__.py
poetrylucidtest/demo.py
poetrylucidtest-0.1.1.dist-info/METADATA
poetrylucidtest-0.1.1.dist-info/WHEEL
poetrylucidtest-0.1.1.dist-info/RECORD
