Metadata-Version: 2.1
Name: poetrylucidtest
Version: 0.1.1
Summary: 
Author: Gang Huang
Author-email: huanggang.dut@gmail.com
Requires-Python: ==3.*
Classifier: Programming Language :: Python :: 3
Classifier: Programming Language :: Python :: 3.4
Classifier: Programming Language :: Python :: 3.5
Classifier: Programming Language :: Python :: 3.6
Classifier: Programming Language :: Python :: 3.7
Classifier: Programming Language :: Python :: 3.8
Classifier: Programming Language :: Python :: 3.9
Classifier: Programming Language :: Python :: 3.10
Classifier: Programming Language :: Python :: 3.11
Requires-Dist: pyglet (>=2.0.9,<3.0.0)
